spacy_lookup/__init__.py
spacy_lookup/about.py
tests/__init__.py
tests/test_entities.py
spacy_lookup-0.1.0.dist-info/LICENSE
spacy_lookup-0.1.0.dist-info/METADATA
spacy_lookup-0.1.0.dist-info/WHEEL
spacy_lookup-0.1.0.dist-info/top_level.txt
spacy_lookup-0.1.0.dist-info/RECORD
