Metadata-Version: 2.1
Name: spacy-lookup
Version: 0.1.0
Summary: spaCy pipeline component for Named Entity Recognition based on dictionaries.
Home-page: https://github.com/mpuig/spacy-lookup
Author: Marc Puig
Author-email: marc.puig@gmail.com
License: MIT
Platform: UNKNOWN
Requires-Dist: spacy (<3.0.0,>=2.0.16)
Requires-Dist: flashtext (>=2.7)
